{"contact_email":"hi@lettherebeads.io","contact_address":"Za Ženskými domovy 3379/1, Praha 5, Czech republic","version":"1.0","sellers":[{"seller_id":"0","name":"lettherebeads.io","domain":"lettherebeads.io","seller_type":"BOTH","is_confidential":0},{"seller_id":"140","name":"BurdaMedia Extra s.r.o.","domain":"burda.cz","seller_type":"publisher"},{"seller_id":"152","name":"Economia, a.s.","domain":"economia.cz","seller_type":"publisher"},{"seller_id":"179","name":"MAFRA, a.s.","domain":"mafra.cz","seller_type":"publisher"},{"seller_id":"221","name":"Mediadyn Kft.","domain":"mediadyn.hu","seller_type":"publisher"},{"seller_id":"232","name":"Ringier Serbia doo","domain":"ringier.rs","seller_type":"publisher"},{"seller_id":"256","name":"Future Media Partners","domain":"futuremediapartners.com","seller_type":"publisher"},{"seller_id":"269","name":"5 elements International SRL","domain":"fiveelementsdigital.com","seller_type":"publisher"},{"seller_id":"278","name":"Lux Television and Radio Company","domain":"24tv.ua","seller_type":"publisher"},{"seller_id":"287","name":"POMO Media Group s.r.o.","domain":"csfd.cz","seller_type":"publisher"},{"seller_id":"305","name":"Global Notícias - Media Group, S.A","domain":"globalmediagroup.pt","seller_type":"publisher"},{"seller_id":"308","name":"OFF Media JSC","domain":"offmedia.bg","seller_type":"publisher"},{"seller_id":"311","name":"Investor.BG AD","domain":"ibg.bg","seller_type":"publisher"},{"seller_id":"314","name":"MediaRey, SE","domain":"forbes.cz","seller_type":"publisher"},{"seller_id":"341","name":"Ringier Slovakia Media s.r.o.","domain":"ringier.sk","seller_type":"publisher"},{"seller_id":"344","name":"Otavamedia Oy","domain":"otavamedia.fi","seller_type":"publisher"},{"seller_id":"347","name":"Kurzy.cz, spol. s r.o.","domain":"kurzy.cz","seller_type":"publisher"},{"seller_id":"356","name":"Dir.BG AD","domain":"company.dir.bg","seller_type":"publisher"},{"seller_id":"359","name":"The Irish Times DAC","domain":"irishtimes.com","seller_type":"publisher"},{"seller_id":"368","name":"bTV Media Group EAD","domain":"btv.bg","seller_type":"publisher"},{"seller_id":"384","name":"Styria Media si, d.o.o.","domain":"styria-media.si","seller_type":"publisher"},{"seller_id":"399","name":"Ringier Hungary Kft.","domain":"ringier.hu","seller_type":"publisher"},{"seller_id":"411","name":"Internet Group d.o.o.","domain":"internetgroup.rs","seller_type":"publisher"},{"seller_id":"417","name":"MOTUS MEDIA d.o.o.","domain":"motus-media.hr","seller_type":"publisher"},{"seller_id":"426","name":"Gremi Media SA","domain":"gremimedia.pl","seller_type":"publisher"},{"seller_id":"429","name":"Quable B.V.","domain":"quable.nl","seller_type":"publisher"},{"seller_id":"432","name":"Bonnier Business (Polska) sp. z o.o.","domain":"bonnier.pl","seller_type":"publisher"},{"seller_id":"462","name":"Sales Contact Kft.","domain":"adaptivemedia.hu","seller_type":"intermediary"},{"seller_id":"472","name":"Van Másik Kft.","domain":"telex.hu","seller_type":"publisher"},{"seller_id":"527","name":"Agencija Hercegovina Info","domain":"hercegovina.info","seller_type":"publisher"},{"seller_id":"551","name":"Brand & Standard Capital Kft.","domain":null,"seller_type":null},{"seller_id":"596","name":"Central Médiacsoport Zrt.","domain":"https://centralmediacsoport.hu/","seller_type":"publisher"},{"seller_id":"636","name":"Oslobođenje d.o.o.","domain":"oslobodjenje.ba","seller_type":"publisher"},{"seller_id":"651","name":"Dogus Media Group","domain":null,"seller_type":"publisher"},{"seller_id":"657","name":"SEKTOR 51 d.o.o.","domain":"bljesak.info","seller_type":"publisher"},{"seller_id":"686","name":"Wireless Media LLC","domain":"https://wm.group/","seller_type":"publisher"}]}