{"contact_email": "Publisher@visualads.com","contact_address":"Turkey, Istanbul","last_update":"27/06/2025","sellers":
[
    {
        "seller_id": 1065550,
        "name": "Anish",
        "domain": "Anish",
        "seller_type": "PUBLISHER"
    },
    {
        "seller_id": 1130475238,
        "name": "Sonix",
        "domain": "Sonix",
        "seller_type": "PUBLISHER"
    },
    {
        "seller_id": 137142775,
        "name": "8BGM",
        "domain": "8BGM",
        "seller_type": "PUBLISHER"
    },
    {
        "seller_id": 21617902087,
        "name": "VpnJantit",
        "domain": "VpnJantit",
        "seller_type": "PUBLISHER"
    },
    {
        "seller_id": 21725906976,
        "name": "Load",
        "domain": "Load",
        "seller_type": "PUBLISHER"
    },
    {
        "seller_id": 21747990212,
        "name": "Bangla",
        "domain": "Bangla",
        "seller_type": "PUBLISHER"
    },
    {
        "seller_id": 21807606712,
        "name": "Nedr",
        "domain": "Nedr",
        "seller_type": "PUBLISHER"
    },
    {
        "seller_id": 21888964095,
        "name": "2689Web",
        "domain": "2689Web",
        "seller_type": "PUBLISHER"
    },
    {
        "seller_id": 21920055606,
        "name": "Diaspora",
        "domain": "Diaspora",
        "seller_type": "PUBLISHER"
    },
    {
        "seller_id": 22135044411,
        "name": "LoadZone",
        "domain": "LoadZone",
        "seller_type": "PUBLISHER"
    },
    {
        "seller_id": 22182076066,
        "name": "Zaluschi",
        "domain": "Zaluschi",
        "seller_type": "PUBLISHER"
    },
    {
        "seller_id": 22441662584,
        "name": "Mcube",
        "domain": "Mcube",
        "seller_type": "PUBLISHER"
    },
    {
        "seller_id": 22551806552,
        "name": "Mehul",
        "domain": "Mehul",
        "seller_type": "PUBLISHER"
    },
    {
        "seller_id": 22687269675,
        "name": "Hasan_GoodS2",
        "domain": "Hasan_GoodS2",
        "seller_type": "PUBLISHER"
    },
    {
        "seller_id": 22695661998,
        "name": "Farahan71",
        "domain": "Farahan71",
        "seller_type": "PUBLISHER"
    },
    {
        "seller_id": 22703299625,
        "name": "Mas",
        "domain": "Mas",
        "seller_type": "PUBLISHER"
    },
    {
        "seller_id": 22732432843,
        "name": "Mizael",
        "domain": "Mizael",
        "seller_type": "PUBLISHER"
    },
    {
        "seller_id": 22733489401,
        "name": "Legalversity",
        "domain": "Legalversity",
        "seller_type": "PUBLISHER"
    },
    {
        "seller_id": 22759260688,
        "name": "Amirghaly",
        "domain": "Amirghaly",
        "seller_type": "PUBLISHER"
    },
    {
        "seller_id": 22778044319,
        "name": "Vijvachh2566",
        "domain": "Vijvachh2566",
        "seller_type": "PUBLISHER"
    },
    {
        "seller_id": 22820144913,
        "name": "PlayerJet",
        "domain": "PlayerJet",
        "seller_type": "PUBLISHER"
    },
    {
        "seller_id": 22834577590,
        "name": "TompiAdx",
        "domain": "TompiAdx",
        "seller_type": "PUBLISHER"
    },
    {
        "seller_id": 22857857566,
        "name": "Vesta",
        "domain": "Vesta",
        "seller_type": "PUBLISHER"
    },
    {
        "seller_id": 22871063881,
        "name": "Burny_GM",
        "domain": "Burny_GM",
        "seller_type": "PUBLISHER"
    },
    {
        "seller_id": 22874478886,
        "name": "Tarmana",
        "domain": "Tarmana",
        "seller_type": "PUBLISHER"
    },
    {
        "seller_id": 22887955879,
        "name": "Search Pika",
        "domain": "Search Pika",
        "seller_type": "PUBLISHER"
    },
    {
        "seller_id": 22912234138,
        "name": "DigiSolutions",
        "domain": "DigiSolutions",
        "seller_type": "PUBLISHER"
    },
    {
        "seller_id": 22913530906,
        "name": "Gamerstyme",
        "domain": "Gamerstyme",
        "seller_type": "PUBLISHER"
    },
    {
        "seller_id": 22920411466,
        "name": "Vrunda",
        "domain": "Vrunda",
        "seller_type": "PUBLISHER"
    },
    {
        "seller_id": 22924319535,
        "name": "GoyaniT",
        "domain": "GoyaniT",
        "seller_type": "PUBLISHER"
    },
    {
        "seller_id": 22964865989,
        "name": "100NewsUp",
        "domain": "100NewsUp",
        "seller_type": "PUBLISHER"
    },
    {
        "seller_id": 22969205623,
        "name": "T2Blive",
        "domain": "T2Blive",
        "seller_type": "PUBLISHER"
    },
    {
        "seller_id": 22987384947,
        "name": "Atul",
        "domain": "Atul",
        "seller_type": "PUBLISHER"
    },
    {
        "seller_id": 22994532650,
        "name": "Redazione",
        "domain": "Redazione",
        "seller_type": "PUBLISHER"
    },
    {
        "seller_id": 23001590860,
        "name": "VivekMore",
        "domain": "VivekMore",
        "seller_type": "PUBLISHER"
    },
    {
        "seller_id": 23003406669,
        "name": "Raman",
        "domain": "Raman",
        "seller_type": "PUBLISHER"
    },
    {
        "seller_id": 23020946460,
        "name": "EspxMedia",
        "domain": "EspxMedia",
        "seller_type": "PUBLISHER"
    },
    {
        "seller_id": 23023386341,
        "name": "Farshub",
        "domain": "Farshub",
        "seller_type": "PUBLISHER"
    },
    {
        "seller_id": 23029069462,
        "name": "DivanApp",
        "domain": "DivanApp",
        "seller_type": "PUBLISHER"
    },
    {
        "seller_id": 23029811513,
        "name": "Liem",
        "domain": "Liem",
        "seller_type": "PUBLISHER"
    },
    {
        "seller_id": 23032928980,
        "name": "MonoAdsUp",
        "domain": "MonoAdsUp",
        "seller_type": "PUBLISHER"
    },
    {
        "seller_id": 23036127379,
        "name": "YeniAds",
        "domain": "YeniAds",
        "seller_type": "PUBLISHER"
    },
    {
        "seller_id": 23036305310,
        "name": "Joey_Ed",
        "domain": "Joey_Ed",
        "seller_type": "PUBLISHER"
    },
    {
        "seller_id": 23038004921,
        "name": "AdOpsPub",
        "domain": "AdOpsPub",
        "seller_type": "PUBLISHER"
    },
    {
        "seller_id": 23038203128,
        "name": "MonMor",
        "domain": "MonMor",
        "seller_type": "PUBLISHER"
    },
    {
        "seller_id": 23045439724,
        "name": "HiloAds",
        "domain": "HiloAds",
        "seller_type": "PUBLISHER"
    },
    {
        "seller_id": 23050256432,
        "name": "Luciano",
        "domain": "Luciano",
        "seller_type": "PUBLISHER"
    },
    {
        "seller_id": 23054947776,
        "name": "Shahr_FRNG",
        "domain": "Shahr_FRNG",
        "seller_type": "PUBLISHER"
    },
    {
        "seller_id": 23056667078,
        "name": "Taimur_E",
        "domain": "Taimur_E",
        "seller_type": "PUBLISHER"
    },
    {
        "seller_id": 23058938682,
        "name": "GAM2",
        "domain": "GAM2",
        "seller_type": "PUBLISHER"
    },
    {
        "seller_id": 23059350624,
        "name": "Reklam",
        "domain": "Reklam",
        "seller_type": "PUBLISHER"
    },
    {
        "seller_id": 23061699857,
        "name": "AMixr3",
        "domain": "AMixr3",
        "seller_type": "PUBLISHER"
    },
    {
        "seller_id": 23062446453,
        "name": "AliHamza",
        "domain": "AliHamza",
        "seller_type": "PUBLISHER"
    },
    {
        "seller_id": 23090668790,
        "name": "Potns",
        "domain": "Potns",
        "seller_type": "PUBLISHER"
    },
    {
        "seller_id": 23092896625,
        "name": "Results.Shiksha",
        "domain": "Results.Shiksha",
        "seller_type": "PUBLISHER"
    },
    {
        "seller_id": 23093007875,
        "name": "Angel_M",
        "domain": "Angel_M",
        "seller_type": "PUBLISHER"
    },
    {
        "seller_id": 23093371074,
        "name": "111Team",
        "domain": "111Team",
        "seller_type": "PUBLISHER"
    },
    {
        "seller_id": 23098318735,
        "name": "Tahir",
        "domain": "Tahir",
        "seller_type": "PUBLISHER"
    },
    {
        "seller_id": 23098434261,
        "name": "Nishith",
        "domain": "Nishith",
        "seller_type": "PUBLISHER"
    },
    {
        "seller_id": 23098884323,
        "name": "SeeDrama",
        "domain": "SeeDrama",
        "seller_type": "PUBLISHER"
    },
    {
        "seller_id": 23100894716,
        "name": "PubFuture",
        "domain": "PubFuture",
        "seller_type": "PUBLISHER"
    },
    {
        "seller_id": 23109849063,
        "name": "Beauty_Sal3",
        "domain": "Beauty_Sal3",
        "seller_type": "PUBLISHER"
    },
    {
        "seller_id": 23112501897,
        "name": "RohitKumar",
        "domain": "RohitKumar",
        "seller_type": "PUBLISHER"
    },
    {
        "seller_id": 23113634242,
        "name": "Anord",
        "domain": "Anord",
        "seller_type": "PUBLISHER"
    },
    {
        "seller_id": 23130406118,
        "name": "UkakAds",
        "domain": "UkakAds",
        "seller_type": "PUBLISHER"
    },
    {
        "seller_id": 23130985999,
        "name": "Farz_Slic",
        "domain": "Farz_Slic",
        "seller_type": "PUBLISHER"
    },
    {
        "seller_id": 23131237507,
        "name": "GMA Game",
        "domain": "GMA Game",
        "seller_type": "PUBLISHER"
    },
    {
        "seller_id": 23131246468,
        "name": "NewGame RN",
        "domain": "NewGame RN",
        "seller_type": "PUBLISHER"
    },
    {
        "seller_id": 23131310834,
        "name": "MonoAds",
        "domain": "MonoAds",
        "seller_type": "PUBLISHER"
    },
    {
        "seller_id": 23131358654,
        "name": "Samur_Apps",
        "domain": "Samur_Apps",
        "seller_type": "PUBLISHER"
    },
    {
        "seller_id": 23131396845,
        "name": "Bistoon",
        "domain": "Bistoon",
        "seller_type": "PUBLISHER"
    },
    {
        "seller_id": 23131518395,
        "name": "HemTop",
        "domain": "HemTop",
        "seller_type": "PUBLISHER"
    },
    {
        "seller_id": 23131638115,
        "name": "NikGame",
        "domain": "NikGame",
        "seller_type": "PUBLISHER"
    },
    {
        "seller_id": 23131678597,
        "name": "LadGame",
        "domain": "LadGame",
        "seller_type": "PUBLISHER"
    },
    {
        "seller_id": 7586855,
        "name": "Layarhijau",
        "domain": "Layarhijau",
        "seller_type": "PUBLISHER"
    },
    {
        "seller_id": 9238721,
        "name": "Listanza",
        "domain": "Listanza",
        "seller_type": "PUBLISHER"
    },
    {
        "seller_id": 23131681717,
        "name": "QevinApp",
        "domain": "QevinApp",
        "seller_type": "PUBLISHER"
    },
    {
        "seller_id": 23131683901,
        "name": "NextGame",
        "domain": "NextGame",
        "seller_type": "PUBLISHER"
    },
    {
        "seller_id": 23131751677,
        "name": "ShahriShah",
        "domain": "ShahriShah",
        "seller_type": "PUBLISHER"
    },
    {
        "seller_id": 23131816588,
        "name": "YourtenG",
        "domain": "YourtenG",
        "seller_type": "PUBLISHER"
    },
    {
        "seller_id": 23131817569,
        "name": "FotonGames",
        "domain": "FotonGames",
        "seller_type": "PUBLISHER"
    },
    {
        "seller_id": 23131905636,
        "name": "DeveloperApps",
        "domain": "DeveloperApps",
        "seller_type": "PUBLISHER"
    },
    {
        "seller_id": 23132038976,
        "name": "Ghodrat.Ads.CO",
        "domain": "Ghodrat.Ads.CO",
        "seller_type": "PUBLISHER"
    },
    {
        "seller_id": 23132042735,
        "name": "JumpDev",
        "domain": "JumpDev",
        "seller_type": "PUBLISHER"
    },
    {
        "seller_id": 23132114502,
        "name": "MajdApp.1114",
        "domain": "MajdApp.1114",
        "seller_type": "PUBLISHER"
    },
    {
        "seller_id": 23132139915,
        "name": "NaniGame2024",
        "domain": "NaniGame2024",
        "seller_type": "PUBLISHER"
    },
    {
        "seller_id": 23132162460,
        "name": "Sadegh Ar",
        "domain": "Sadegh Ar",
        "seller_type": "PUBLISHER"
    },
    {
        "seller_id": 23132177018,
        "name": "Rdcco",
        "domain": "Rdcco",
        "seller_type": "PUBLISHER"
    },
    {
        "seller_id": 23132559741,
        "name": "DownDev",
        "domain": "DownDev",
        "seller_type": "PUBLISHER"
    },
    {
        "seller_id": 23132712192,
        "name": "OrgiGame",
        "domain": "OrgiGame",
        "seller_type": "PUBLISHER"
    },
    {
        "seller_id": 23132726637,
        "name": "AppsShopsCot",
        "domain": "AppsShopsCot",
        "seller_type": "PUBLISHER"
    },
    {
        "seller_id": 23132734254,
        "name": "Uko",
        "domain": "Uko",
        "seller_type": "PUBLISHER"
    },
    {
        "seller_id": 23134240927,
        "name": "HawaiGame",
        "domain": "HawaiGame",
        "seller_type": "PUBLISHER"
    },
    {
        "seller_id": 23134903764,
        "name": "Ken",
        "domain": "Ken",
        "seller_type": "PUBLISHER"
    },
    {
        "seller_id": 23136942205,
        "name": "JoulTheDeveloper",
        "domain": "JoulTheDeveloper",
        "seller_type": "PUBLISHER"
    },
    {
        "seller_id": 23137452591,
        "name": "Konstantygorski3",
        "domain": "Konstantygorski3",
        "seller_type": "PUBLISHER"
    },
    {
        "seller_id": 23138206966,
        "name": "VMH",
        "domain": "VMH",
        "seller_type": "PUBLISHER"
    },
    {
        "seller_id": 23138923328,
        "name": "Kolorowey",
        "domain": "Kolorowey",
        "seller_type": "PUBLISHER"
    },
    {
        "seller_id": 23139377020,
        "name": "WowApp",
        "domain": "WowApp",
        "seller_type": "PUBLISHER"
    },
    {
        "seller_id": 23139406194,
        "name": "Softecks",
        "domain": "Softecks",
        "seller_type": "PUBLISHER"
    },
    {
        "seller_id": 23142029869,
        "name": "AmAli",
        "domain": "AmAli",
        "seller_type": "PUBLISHER"
    },
    {
        "seller_id": 23142031657,
        "name": "MMir",
        "domain": "MMir",
        "seller_type": "PUBLISHER"
    },
    {
        "seller_id": 23142964445,
        "name": "BestDeveloper",
        "domain": "BestDeveloper",
        "seller_type": "PUBLISHER"
    },
    {
        "seller_id": 23143083900,
        "name": "MMir2",
        "domain": "MMir2",
        "seller_type": "PUBLISHER"
    },
    {
        "seller_id": 23143324952,
        "name": "Behyar_Apps",
        "domain": "Behyar_Apps",
        "seller_type": "PUBLISHER"
    },
    {
        "seller_id": 23144714721,
        "name": "Fboi",
        "domain": "Fboi",
        "seller_type": "PUBLISHER"
    },
    {
        "seller_id": 23145726761,
        "name": "William",
        "domain": "William",
        "seller_type": "PUBLISHER"
    },
    {
        "seller_id": 23147584804,
        "name": "Samn_Tel",
        "domain": "Samn_Tel",
        "seller_type": "PUBLISHER"
    },
    {
        "seller_id": 23147599954,
        "name": "ARK",
        "domain": "ARK",
        "seller_type": "PUBLISHER"
    },
    {
        "seller_id": 23148212747,
        "name": "Rasan",
        "domain": "Rasan",
        "seller_type": "PUBLISHER"
    },
    {
        "seller_id": 23150294724,
        "name": "MehranH",
        "domain": "MehranH",
        "seller_type": "PUBLISHER"
    },
    {
        "seller_id": 23154388855,
        "name": "HQZ",
        "domain": "HQZ",
        "seller_type": "PUBLISHER"
    },
    {
        "seller_id": 23161097448,
        "name": "Haghigh_UKR",
        "domain": "Haghigh_UKR",
        "seller_type": "PUBLISHER"
    },
    {
        "seller_id": 23161325500,
        "name": "SokkerPro",
        "domain": "SokkerPro",
        "seller_type": "PUBLISHER"
    },
    {
        "seller_id": 23162774257,
        "name": "Flytant",
        "domain": "Flytant",
        "seller_type": "PUBLISHER"
    },
    {
        "seller_id": 23163051934,
        "name": "MrApp",
        "domain": "MrApp",
        "seller_type": "PUBLISHER"
    },
    {
        "seller_id": 23163281959,
        "name": "Beauty_Sal2",
        "domain": "Beauty_Sal2",
        "seller_type": "PUBLISHER"
    },
    {
        "seller_id": 23167256779,
        "name": "Varun_Sa",
        "domain": "Varun_Sa",
        "seller_type": "PUBLISHER"
    },
    {
        "seller_id": 23167889868,
        "name": "Haghigh_UKR2",
        "domain": "Haghigh_UKR2",
        "seller_type": "PUBLISHER"
    },
    {
        "seller_id": 23169250504,
        "name": "AmAli2",
        "domain": "AmAli2",
        "seller_type": "PUBLISHER"
    },
    {
        "seller_id": 23169549745,
        "name": "Mahmoud",
        "domain": "Mahmoud",
        "seller_type": "PUBLISHER"
    },
    {
        "seller_id": 23170860382,
        "name": "SirvAhmad",
        "domain": "SirvAhmad",
        "seller_type": "PUBLISHER"
    },
    {
        "seller_id": 23171795559,
        "name": "KomeilUKR",
        "domain": "KomeilUKR",
        "seller_type": "PUBLISHER"
    },
    {
        "seller_id": 23173092547,
        "name": "Krisdonga4",
        "domain": "Krisdonga4",
        "seller_type": "PUBLISHER"
    },
    {
        "seller_id": 23173116318,
        "name": "DTHL",
        "domain": "DTHL",
        "seller_type": "PUBLISHER"
    },
    {
        "seller_id": 23173721432,
        "name": "AmitKumar",
        "domain": "AmitKumar",
        "seller_type": "PUBLISHER"
    },
    {
        "seller_id": 23176909840,
        "name": "Nishith_2",
        "domain": "Nishith_2",
        "seller_type": "PUBLISHER"
    },
    {
        "seller_id": 23190483258,
        "name": "Atul_R",
        "domain": "Atul_R",
        "seller_type": "PUBLISHER"
    },
    {
        "seller_id": 23197626612,
        "name": "Sirvan",
        "domain": "Sirvan",
        "seller_type": "PUBLISHER"
    },
    {
        "seller_id": 23200286145,
        "name": "VMHUAE",
        "domain": "VMHUAE",
        "seller_type": "PUBLISHER"
    },
    {
        "seller_id": 23200699137,
        "name": "VPT",
        "domain": "VPT",
        "seller_type": "PUBLISHER"
    },
    {
        "seller_id": 23200721495,
        "name": "ANKITR",
        "domain": "ANKITR",
        "seller_type": "PUBLISHER"
    },
    {
        "seller_id": 23201151789,
        "name": "PinVpn",
        "domain": "PinVpn",
        "seller_type": "PUBLISHER"
    },
    {
        "seller_id": 23201348267,
        "name": "Rhdy54055",
        "domain": "Rhdy54055",
        "seller_type": "PUBLISHER"
    },
    {
        "seller_id": 23202541029,
        "name": "AmAl3",
        "domain": "AmAl3",
        "seller_type": "PUBLISHER"
    },
    {
        "seller_id": 23203501990,
        "name": "MrApp2",
        "domain": "MrApp2",
        "seller_type": "PUBLISHER"
    },
    {
        "seller_id": 23204533644,
        "name": "AdsVictory",
        "domain": "AdsVictory",
        "seller_type": "PUBLISHER"
    },
    {
        "seller_id": 23204814943,
        "name": "M10news",
        "domain": "M10news",
        "seller_type": "PUBLISHER"
    },
    {
        "seller_id": 23207811025,
        "name": "RovvaApps",
        "domain": "RovvaApps",
        "seller_type": "PUBLISHER"
    },
    {
        "seller_id": 23209125895,
        "name": "Frezaei",
        "domain": "Frezaei",
        "seller_type": "PUBLISHER"
    },
    {
        "seller_id": 23209327504,
        "name": "ChandanSingh",
        "domain": "ChandanSingh",
        "seller_type": "PUBLISHER"
    },
    {
        "seller_id": 23212977596,
        "name": "AkhtarAziz",
        "domain": "AkhtarAziz",
        "seller_type": "PUBLISHER"
    },
    {
        "seller_id": 23213300113,
        "name": "Yaz_Atom",
        "domain": "Yaz_Atom",
        "seller_type": "PUBLISHER"
    },
    {
        "seller_id": 23214174052,
        "name": "AyatGh_UAE",
        "domain": "AyatGh_UAE",
        "seller_type": "PUBLISHER"
    },
    {
        "seller_id": 23218604577,
        "name": "DUBAI_Hayat",
        "domain": "DUBAI_Hayat",
        "seller_type": "PUBLISHER"
    },
    {
        "seller_id": 23269955826,
        "name": "Tetyana_UKR",
        "domain": "Tetyana_UKR",
        "seller_type": "PUBLISHER"
    },
    {
        "seller_id": 23270050601,
        "name": "Skyline_UK",
        "domain": "Skyline_UK",
        "seller_type": "PUBLISHER"
    },
    {
        "seller_id": 23275987479,
        "name": "Strongirl.dev",
        "domain": "Strongirl.dev",
        "seller_type": "PUBLISHER"
    },
    {
        "seller_id": 23277468296,
        "name": "Idtv.lidia81",
        "domain": "Idtv.lidia81",
        "seller_type": "PUBLISHER"
    },
    {
        "seller_id": 23278074690,
        "name": "SilentBridge",
        "domain": "SilentBridge",
        "seller_type": "PUBLISHER"
    },
    {
        "seller_id": 23279159759,
        "name": "Haghigh_UKR3",
        "domain": "Haghigh_UKR3",
        "seller_type": "PUBLISHER"
    },
    {
        "seller_id": 23280821293,
        "name": "Vaydm.nanov",
        "domain": "Vaydm.nanov",
        "seller_type": "PUBLISHER"
    },
    {
        "seller_id": 23281247488,
        "name": "Quantum USA",
        "domain": "Quantum USA",
        "seller_type": "PUBLISHER"
    },
    {
        "seller_id": 23284094497,
        "name": "Dublex.suns",
        "domain": "Dublex.suns",
        "seller_type": "PUBLISHER"
    },
    {
        "seller_id": 23284325335,
        "name": "Topcoders",
        "domain": "Topcoders",
        "seller_type": "PUBLISHER"
    },
    {
        "seller_id": 23284594495,
        "name": "Adion.muchi",
        "domain": "Adion.muchi",
        "seller_type": "PUBLISHER"
    },
    {
        "seller_id": 23284675528,
        "name": "Behtop.dev",
        "domain": "Behtop.dev",
        "seller_type": "PUBLISHER"
    },
    {
        "seller_id": 23284675561,
        "name": "Inan.technol",
        "domain": "Inan.technol",
        "seller_type": "PUBLISHER"
    },
    {
        "seller_id": 23287745414,
        "name": "Dimi.gameis",
        "domain": "Dimi.gameis",
        "seller_type": "PUBLISHER"
    },
    {
        "seller_id": 23288086308,
        "name": "Rudenkovocher",
        "domain": "Rudenkovocher",
        "seller_type": "PUBLISHER"
    },
    {
        "seller_id": 334505831,
        "name": "Exent",
        "domain": "Exent",
        "seller_type": "PUBLISHER"
    },
    {
        "seller_id": 334817110,
        "name": "TvSeason",
        "domain": "TvSeason",
        "seller_type": "PUBLISHER"
    },
    {
        "seller_id": 45852657,
        "name": "JCB",
        "domain": "JCB",
        "seller_type": "PUBLISHER"
    },
    {
        "seller_id": 23288775988,
        "name": "Vikivokanov",
        "domain": "Vikivokanov",
        "seller_type": "PUBLISHER"
    },
    {
        "seller_id": 23288776126,
        "name": "Samserc.neo",
        "domain": "Samserc.neo",
        "seller_type": "PUBLISHER"
    },
    {
        "seller_id": 23290023873,
        "name": "Monche.lete",
        "domain": "Monche.lete",
        "seller_type": "PUBLISHER"
    },
    {
        "seller_id": 22853093617 ,
        "name": "Musk",
        "domain": "Musk",
        "seller_type": "PUBLISHER"
    },
    {
        "seller_id": 23013544364 ,
        "name": "Sanket",
        "domain": "Sanket",
        "seller_type": "PUBLISHER"
    },
    {
        "seller_id": 23064684401 ,
        "name": "EasyCal",
        "domain": "EasyCal",
        "seller_type": "PUBLISHER"
    },
    {
        "seller_id": 23131526081 ,
        "name": "AdsMads",
        "domain": "AdsMads",
        "seller_type": "PUBLISHER"
    },
    {
        "seller_id": 23131531634 ,
        "name": "GoAds",
        "domain": "GoAds",
        "seller_type": "PUBLISHER"
    },
    {
        "seller_id": 23132051127 ,
        "name": "ElifYan",
        "domain": "ElifYan",
        "seller_type": "PUBLISHER"
    },
    {
        "seller_id": 23131540691 ,
        "name": "JasAds",
        "domain": "JasAds",
        "seller_type": "PUBLISHER"
    },
    {
        "seller_id": 22819245340 ,
        "name": "Lakatos",
        "domain": "Lakatos",
        "seller_type": "PUBLISHER"
    },
    {
        "seller_id": 23297387922 ,
        "name": "Ticker",
        "domain": "Ticker",
        "seller_type": "PUBLISHER"
    }
    ,
    {
        "seller_id": 22903052954 ,
        "name": "Rswork",
        "domain": "Rswork",
        "seller_type": "PUBLISHER"
    },
    {
        "seller_id": 23007608387 ,
        "name": "KunalKamur",
        "domain": "KunalKamur",
        "seller_type": "PUBLISHER"
    },
    {
        "seller_id": 23164630515 ,
        "name": "Lavkush",
        "domain": "Lavkush",
        "seller_type": "PUBLISHER"
    },
    {
        "seller_id": 22859548824 ,
        "name": "Pratik",
        "domain": "Pratik",
        "seller_type": "PUBLISHER"
    },
    {
        "seller_id": 23299381457 ,
        "name": "Juliana",
        "domain": "Juliana",
        "seller_type": "PUBLISHER"
    },
    {
        "seller_id": 23199205258 ,
        "name": "Vimesh",
        "domain": "Vimesh",
        "seller_type": "PUBLISHER"
    },
    {
        "seller_id": 23269613308 ,
        "name": "Reis",
        "domain": "Reis",
        "seller_type": "PUBLISHER"
    },
    {
        "seller_id": 23299540444 ,
        "name": "Mar.iry",
        "domain": "Mar.iry",
        "seller_type": "PUBLISHER"
    },
    {
        "seller_id": 23300411303 ,
        "name": "ADQI",
        "domain": "ADQI",
        "seller_type": "PUBLISHER"
    },
    {
        "seller_id": 23300855331 ,
        "name": "Wellkosten",
        "domain": "Wellkosten",
        "seller_type": "PUBLISHER"
    },
    {
        "seller_id": 23300813547 ,
        "name": "Huster",
        "domain": "Huster",
        "seller_type": "PUBLISHER"
    },
    {
        "seller_id": 23300649951 ,
        "name": "Jack",
        "domain": "Jack",
        "seller_type": "PUBLISHER"
    },
    {
        "seller_id": 23301707453 ,
        "name": "Nancy.bych11",
        "domain": "Nancy.bych11",
        "seller_type": "PUBLISHER"
    },
    {
        "seller_id": 23301061846 ,
        "name": "Mustang.roza",
        "domain": "Mustang.roza",
        "seller_type": "PUBLISHER"
    },
    {
        "seller_id": 23301794351 ,
        "name": "Deruslten.io",
        "domain": "Deruslten.io",
        "seller_type": "PUBLISHER"
    },
    {
        "seller_id": 23302309653 ,
        "name": "Ps.ukdevelop",
        "domain": "Ps.ukdevelop",
        "seller_type": "PUBLISHER"
    },
    {
        "seller_id": 23304216174 ,
        "name": "Yonger.rtx",
        "domain": "Yonger.rtx",
        "seller_type": "PUBLISHER"
    },
    {
        "seller_id": 23303807591 ,
        "name": "Yeloside.it",
        "domain": "Yeloside.it",
        "seller_type": "PUBLISHER"
    },
    {
        "seller_id": 23302865342 ,
        "name": "Ferfertime",
        "domain": "Ferfertime",
        "seller_type": "PUBLISHER"
    },
    {
        "seller_id": 23297852338 ,
        "name": "Dailybrewlab",
        "domain": "Dailybrewlab",
        "seller_type": "PUBLISHER"
    },
    {
        "seller_id": 23305926210 ,
        "name": "AmAli4",
        "domain": "AmAli4",
        "seller_type": "PUBLISHER"
    },
    {
        "seller_id": 23131572389 ,
        "name": "SajGame",
        "domain": "SajGame",
        "seller_type": "PUBLISHER"
    },
    {
        "seller_id": 23307419004 ,
        "name": "Solderapp.never",
        "domain": "Solderapp.never",
        "seller_type": "PUBLISHER"
    },
    {
        "seller_id": 23307419793 ,
        "name": "Shuten",
        "domain": "Shuten",
        "seller_type": "PUBLISHER"
    },
    {
        "seller_id": 23306684869 ,
        "name": "Barberoleks",
        "domain": "Barberoleks",
        "seller_type": "PUBLISHER"
    },
    {
        "seller_id": 23309802784 ,
        "name": "Shever.ivanz",
        "domain": "Shever.ivanz",
        "seller_type": "PUBLISHER"
    },
    {
        "seller_id": 23309663612 ,
        "name": "Antireksor",
        "domain": "Antireksor",
        "seller_type": "PUBLISHER"
    },
    {
        "seller_id": 23312022222 ,
        "name": "Alton.mask",
        "domain": "Alton.mask",
        "seller_type": "PUBLISHER"
    },
    {
        "seller_id": 23312022000 ,
        "name": "Bepgeonice",
        "domain": "Bepgeonice",
        "seller_type": "PUBLISHER"
    },
    {
        "seller_id": 23313172864 ,
        "name": "Nazarkhymchenko",
        "domain": "Nazarkhymchenko",
        "seller_type": "PUBLISHER"
    },
    {
        "seller_id": 23301060469 ,
        "name": "Kaziv",
        "domain": "Kaziv",
        "seller_type": "PUBLISHER"
    },
    {
        "seller_id": 23306315166 ,
        "name": "GamNet",
        "domain": "GamNet",
        "seller_type": "PUBLISHER"
    },
     {
        "seller_id": 23305322599 ,
        "name": "Jaimin",
        "domain": "Jaimin",
        "seller_type": "PUBLISHER"
    },
    {
        "seller_id": 23316361322 ,
        "name": "Belanh",
        "domain": "Belanh",
        "seller_type": "PUBLISHER"
    },
    {
        "seller_id": 23317870447 ,
        "name": "Gorotineon",
        "domain": "Gorotineon",
        "seller_type": "PUBLISHER"
    },
    {
        "seller_id": 23318800023 ,
        "name": "Fried.natali",
        "domain": "Fried.natali",
        "seller_type": "PUBLISHER"
    },
    {
        "seller_id": 23318800545 ,
        "name": "Lksndrbiliak",
        "domain": "Lksndrbiliak",
        "seller_type": "PUBLISHER"
    },
    {
        "seller_id": 23319015588 ,
        "name": "Dorofieievayana4",
        "domain": "Dorofieievayana4",
        "seller_type": "PUBLISHER"
    },
    {
        "seller_id": 23319003425 ,
        "name": "Fordermos.ay",
        "domain": "Fordermos.ay",
        "seller_type": "PUBLISHER"
    },
    {
        "seller_id": 23319735609 ,
        "name": "Popcorner.nq",
        "domain": "Popcorner.nq",
        "seller_type": "PUBLISHER"
    },
    {
        "seller_id": 23318625409 ,
        "name": "Andriidudka8",
        "domain": "Andriidudka8",
        "seller_type": "PUBLISHER"
    },
     {
        "seller_id": 23300429249 ,
        "name": "Haniva",
        "domain": "Haniva",
        "seller_type": "PUBLISHER"
    },
    {
        "seller_id": 23145612747 ,
        "name": "Bis2",
        "domain": "Bis2",
        "seller_type": "PUBLISHER"
    },
    {
        "seller_id": 23322683221 ,
        "name": "Balanartapp",
        "domain": "Balanartapp",
        "seller_type": "PUBLISHER"
    },
    {
        "seller_id": 23320220811 ,
        "name": "Ihsobluuu94",
        "domain": "Ihsobluuu94",
        "seller_type": "PUBLISHER"
    },
    {
        "seller_id": 23104420254 ,
        "name": "HomeFoodies",
        "domain": "HomeFoodies",
        "seller_type": "PUBLISHER"
    },
    {
        "seller_id": 23333062548 ,
        "name": "AmAli5",
        "domain": "AmAli5",
        "seller_type": "PUBLISHER"
    },
    {
        "seller_id": 23199590643 ,
        "name": "Bilalonlineads",
        "domain": "Bilalonlineads",
        "seller_type": "PUBLISHER"
    },
    {
        "seller_id": 1020959 ,
        "name": "GoNc",
        "domain": "GoNc",
        "seller_type": "PUBLISHER"
    },
    {
        "seller_id": 128565665 ,
        "name": "Crono8888",
        "domain": "Crono8888",
        "seller_type": "PUBLISHER"
    },
    {
        "seller_id": 23319898965 ,
        "name": "ShdowFort",
        "domain": "ShdowFort",
        "seller_type": "PUBLISHER"
    },
    {
        "seller_id": 23320763947 ,
        "name": "Mayurms022",
        "domain": "Mayurms022",
        "seller_type": "PUBLISHER"
    },
    {
        "seller_id": 23334810921 ,
        "name": "Browsersimontok",
        "domain": "Browsersimontok",
        "seller_type": "PUBLISHER"
    }
]}