{
  "version": "1.0",
  "contact_email": "hello@streamstak.com",
  "contact_address": "116 Washington Avenue, Third Floor, North Haven, CT 06473",
  "sellers": [
    {"name": "Streamstak", "domain": "streamstak.com", "seller_id": "17475", "seller_type": "PUBLISHER"},
    {"name": "Stadium", "domain": "watchstadium.com", "seller_id": "33959", "seller_type": "PUBLISHER"},
    {"name": "Willow TV", "domain": "willow.tv", "seller_id": "51861", "seller_type": "PUBLISHER"},
    {"name": "Fearpix", "domain": "fearpix.com", "seller_id": "51063", "seller_type": "PUBLISHER"},
    {"name": "Samsung TV Plus", "domain": "samsungtvplus.com", "seller_id": "47378", "seller_type": "PUBLISHER"},
    {"name": "Fubo", "domain": "fubo.tv", "seller_id": "21878", "seller_type": "PUBLISHER"},
    {"name": "Xumo", "domain": "xumo.com", "seller_id": "52646", "seller_type": "PUBLISHER"},
    {"name": "Distro TV", "domain": "distro.tv", "seller_id": "16489", "seller_type": "PUBLISHER"},
    {"name": "LG Channels", "domain": "adtech.lgads.tv", "seller_id": "32833", "seller_type": "PUBLISHER"},
    {"name": "Plex", "domain": "plex.tv", "seller_id": "32832", "seller_type": "PUBLISHER"},
    {"name": "Roku", "domain": "roku.com", "seller_id": "38980", "seller_type": "PUBLISHER"},
    {"name": "Local Now", "domain": "localnow.com", "seller_id": "16495", "seller_type": "PUBLISHER"},
    {"name": "FloSports", "domain": "flosports.tv", "seller_id": "25576", "seller_type": "PUBLISHER"},
    {"name": "Yupp TV", "domain": "yupptv.com", "seller_id": "49544", "seller_type": "PUBLISHER"},
    {"name": "TCL", "domain": "tcl.com", "seller_id": "16520", "seller_type": "PUBLISHER"},
    {"name": "Stremium", "domain": "stremium.com", "seller_id": "16504", "seller_type": "PUBLISHER"},
    {"name": "Free Live Sports", "domain": "freelivesports.tv", "seller_id": "49545", "seller_type": "PUBLISHER"},
    {"name": "Sports Tribal TV", "domain": "sportstribal.tv", "seller_id": "17489", "seller_type": "PUBLISHER"},
    {"name": "Freecast", "domain": "freecast.com", "seller_id": "18552", "seller_type": "PUBLISHER"},
    {"name": "Karostream", "domain": "karostream.com", "seller_id": "49542", "seller_type": "PUBLISHER"},
    {"name": "Sling", "domain": "sling.com", "seller_id": "49543", "seller_type": "PUBLISHER"},
    {"name": "PlayNow Media", "domain": "vodtvnow.com", "seller_id": "46192", "seller_type": "PUBLISHER"},
    {"name": "Free Movies Plus", "domain": "freemoviesplus.com", "seller_id": "49293", "seller_type": "PUBLISHER"},
    {"name": "OTT Studio", "domain": "ott.studio", "seller_id": "49285", "seller_type": "PUBLISHER"}
  ]
}
